bruce_models/__init__.py
bruce_models/api/__init__.py
bruce_models/api/api.py
bruce_models/api/bruce_api.py
bruce_models/api/guardian_api.py
bruce_models/client_file/__init__.py
bruce_models/client_file/client_file.py
bruce_models/entity/__init__.py
bruce_models/entity/entity.py
bruce_models/entity/entity_link.py
bruce_models/entity/entity_type.py
bruce_models/scenario/__init__.py
bruce_models/scenario/scenario.py
bruce_models/user/__init__.py
bruce_models/user/session.py
bruce_models-0.1.0.dist-info/METADATA
bruce_models-0.1.0.dist-info/WHEEL
bruce_models-0.1.0.dist-info/top_level.txt
bruce_models-0.1.0.dist-info/RECORD
