Metadata-Version: 2.4
Name: bruce-models
Version: 0.1.0
Summary: This is a library which defines data-models for the Nextspace API and provides functions for communicating with the endpoints.
Author: Matvey Lavrinovich
Author-email: matveylavrinovich@gmail.com
Classifier: Programming Language :: Python :: 3
Classifier: Operating System :: OS Independent
Classifier: Intended Audience :: Developers
Requires-Python: >=3.6
Requires-Dist: requests>=2.0
Dynamic: author
Dynamic: author-email
Dynamic: classifier
Dynamic: description
Dynamic: description-content-type
Dynamic: requires-dist
Dynamic: requires-python
Dynamic: summary
